{
    "station": {
        "city": "Reykjavík",
        "timezone": "Atlantic/Reykjavik",
        "encoding": "utf-8",
        "locale": "en_US.UTF-8",
        "font": "Droid Sans",
        "darkmode": false,
		"api": "Tomorrow.io",
        "lat": 64.1466,
        "lon": -21.9426,
        "units": "metric",
        "lang": "us",
		"in_clouds": "probability",
		"layout": ["maintenant", "main", "daily_xlabel_landscape4", "padding+10", "graph"],
		"graph_objects": ["daily_weather_landscape4"],
		"graph_canvas": "default_landscape",		
        "ramadhan": false
    }
}
